fkir/__init__.py
fkir/ir/__init__.py
fkir/ir/base.py
fkir/ir/graph.py
fkir/ir/node.py
fkir/ir/var.py
fkir/match/__init__.py
fkir/match/pattern.py
fkir-0.1.2.dist-info/LICENSE
fkir-0.1.2.dist-info/METADATA
fkir-0.1.2.dist-info/WHEEL
fkir-0.1.2.dist-info/top_level.txt
fkir-0.1.2.dist-info/RECORD
