Metadata-Version: 2.1
Name: fkir
Version: 0.1.2
Summary: The fucking ir utils
Home-page: https://github.com/OYCN/fuck-ir
Author: oPluss
Author-email: opluss@qq.com
License-File: LICENSE
Requires-Dist: networkx
